annpack/__init__.py
annpack/_header.py
annpack/api.py
annpack/build.py
annpack/cli.py
annpack/logutil.py
annpack/packset.py
annpack/py.typed
annpack/reader.py
annpack/verify.py
annpack/templates/__init__.py
annpack/templates/docs-search/README.md
annpack/templates/docs-search/annpack.json
annpack/templates/docs-search/delta_add.csv
annpack/templates/docs-search/delta_delete.jsonl
annpack/templates/docs-search/docs.csv
annpack/templates/log-search/README.md
annpack/templates/log-search/annpack.json
annpack/templates/log-search/delta_add.csv
annpack/templates/log-search/delta_delete.jsonl
annpack/templates/log-search/logs.csv
annpack/templates/text-search/README.md
annpack/templates/text-search/annpack.json
annpack/templates/text-search/data.csv
annpack/templates/text-search/delta_add.csv
annpack/templates/text-search/delta_delete.jsonl
annpack/ui/__init__.py
annpack/ui/index.html
annpack-0.1.7.dist-info/licenses/LICENSE
annpack-0.1.7.dist-info/METADATA
annpack-0.1.7.dist-info/WHEEL
annpack-0.1.7.dist-info/entry_points.txt
annpack-0.1.7.dist-info/top_level.txt
annpack-0.1.7.dist-info/RECORD
