Metadata-Version: 2.4
Name: annpack
Version: 0.1.7
Summary: ANNPack builder and tools
License-Expression: Apache-2.0
Project-URL: Homepage, https://github.com/Arjun2729/ANNPACK
Project-URL: Issues, https://github.com/Arjun2729/ANNPACK/issues
Classifier: Programming Language :: Python :: 3
Classifier: Operating System :: OS Independent
Requires-Python: >=3.10
License-File: LICENSE
Requires-Dist: polars
Requires-Dist: faiss-cpu
Requires-Dist: numpy
Requires-Dist: cryptography
Provides-Extra: dev
Requires-Dist: pytest; extra == "dev"
Requires-Dist: ruff; extra == "dev"
Requires-Dist: mkdocs; extra == "dev"
Requires-Dist: hypothesis; extra == "dev"
Requires-Dist: build; extra == "dev"
Requires-Dist: twine; extra == "dev"
Requires-Dist: mypy; extra == "dev"
Requires-Dist: pre-commit; extra == "dev"
Provides-Extra: embed
Requires-Dist: sentence-transformers; extra == "embed"
Requires-Dist: torch; extra == "embed"
Requires-Dist: datasets; extra == "embed"
Provides-Extra: registry
Requires-Dist: fastapi; extra == "registry"
Requires-Dist: uvicorn; extra == "registry"
Requires-Dist: pyjwt; extra == "registry"
Requires-Dist: python-multipart; extra == "registry"
Requires-Dist: slowapi; extra == "registry"
Requires-Dist: limits; extra == "registry"
Dynamic: license-file
